DESCRIPTION.rst
MANIFEST.in
setup.py
eztvit/__init__.py
eztvit.egg-info/PKG-INFO
eztvit.egg-info/SOURCES.txt
eztvit.egg-info/dependency_links.txt
eztvit.egg-info/requires.txt
eztvit.egg-info/top_level.txt