Metadata-Version: 1.1
Name: eztvit
Version: 2.0.1
Summary: Screenscraper for https://eztv.it/
Home-page: https://github.com/jaysh/eztvit-python
Author: Jay Shah
Author-email: e+eztvit@jay.sh
License: MIT
Keywords: eztv it api
Platform: UNKNOWN
Classifier: Development Status :: 4 - Beta
Classifier: Environment :: Console
Classifier: Environment :: Web Environment
Classifier: Intended Audience :: Developers
Classifier: License :: OSI Approved :: MIT License
Classifier: Operating System :: MacOS :: MacOS X
Classifier: Operating System :: Microsoft :: Windows
Classifier: Operating System :: POSIX
Classifier: Programming Language :: Python
Classifier: Topic :: Internet :: WWW/HTTP
Classifier: Topic :: Software Development :: Libraries
Classifier: Programming Language :: Python :: 2.7
